setup.cfg
setup.py
ownercheck/__init__.py
ownercheck/apps.py
ownercheck/conf.py
ownercheck/db.py
ownercheck/domains.py
ownercheck.egg-info/PKG-INFO
ownercheck.egg-info/SOURCES.txt
ownercheck.egg-info/dependency_links.txt
ownercheck.egg-info/pbr.json
ownercheck.egg-info/requires.txt
ownercheck.egg-info/top_level.txt