Metadata-Version: 1.1
Name: ownercheck
Version: 0.2.1
Summary: Verify ownership of domain and mobile apps using DNS and other methods
Home-page: https://github.com/FallibleInc/ownercheck
Author: Fallible
Author-email: hello@fallible.co
License: UNKNOWN
Download-URL: https://github.com/FallibleInc/ownercheck/tarball/0.2
Platform: UNKNOWN
